rpp/__init__.py
rpp/decoder.py
rpp/element.py
rpp/encoder.py
rpp/rpp.py
rpp/scanner.py
rpp-0.5.dist-info/LICENSE.rst
rpp-0.5.dist-info/METADATA
rpp-0.5.dist-info/WHEEL
rpp-0.5.dist-info/top_level.txt
rpp-0.5.dist-info/RECORD
