Metadata-Version: 2.1
Name: rpp
Version: 0.5
Summary: Read and write Reaper RPP files with Python.
Author-email: Sviatoslav Abakumov <dust.harvesting@gmail.com>
License: BSD-3-Clause
Project-URL: Source code, https://github.com/Perlence/rpp
Project-URL: Issue tracker, https://github.com/Perlence/rpp/issues
Classifier: Development Status :: 4 - Beta
Classifier: License :: OSI Approved :: BSD License
Classifier: Operating System :: OS Independent
Classifier: Programming Language :: Python :: 3
Classifier: Programming Language :: Python :: 3.7
Classifier: Programming Language :: Python :: 3.8
Classifier: Programming Language :: Python :: 3.9
Classifier: Programming Language :: Python :: 3.10
Classifier: Programming Language :: Python :: 3.11
Classifier: Topic :: Text Processing
Requires-Python: >=3.7
License-File: LICENSE.rst
Requires-Dist: attrs
Requires-Dist: ply
